deep_dict_update/__init__.py
deep_dict_update/deep_dict_update.py
deep_dict_update-0.1.6.dist-info/LICENSE
deep_dict_update-0.1.6.dist-info/METADATA
deep_dict_update-0.1.6.dist-info/WHEEL
deep_dict_update-0.1.6.dist-info/RECORD
