Metadata-Version: 2.1
Name: deep-dict-update
Version: 0.1.6
Summary: Recursively update nested dictionaries with another dictionary
Home-page: https://shivam0110.github.io/deep-dict-update/
License: MIT
Author: Shivam Malpani
Requires-Python: >=3.6,<4.0
Classifier: License :: OSI Approved :: MIT License
Classifier: Programming Language :: Python :: 3
Classifier: Programming Language :: Python :: 3.6
Classifier: Programming Language :: Python :: 3.7
Classifier: Programming Language :: Python :: 3.8
Classifier: Programming Language :: Python :: 3.9
Classifier: Programming Language :: Python :: 3.10
Classifier: Programming Language :: Python :: 3.11
Classifier: Programming Language :: Python :: 3.12
Project-URL: Repository, https://github.com/shivam0110/deep-dict-update
